ansit/__init__.py
ansit/drivers.py
ansit/environment.py
ansit/manifest.py
ansit/util.py
ansit/schemas/change.json
ansit/schemas/manifest.json
ansit-0.0.3.dist-info/METADATA
ansit-0.0.3.dist-info/RECORD
ansit-0.0.3.dist-info/WHEEL
ansit-0.0.3.dist-info/entry_points.txt
ansit-0.0.3.dist-info/top_level.txt
