Metadata-Version: 2.1
Name: ansit
Version: 0.0.3
Summary: Sophisticated tool for testing configuration managment
Home-page: https://github.com/Jakski/ansit
Author: Jakub Pieńkowski
Author-email: jakski@sealcode.org
License: MIT
Platform: UNKNOWN
Classifier: Development Status :: 3 - Alpha
Classifier: Environment :: Console
Classifier: Intended Audience :: System Administrators
Classifier: License :: OSI Approved :: MIT License
Requires-Dist: pyyaml
Requires-Dist: colorlog
Requires-Dist: jsonschema
Requires-Dist: jinja2
Requires-Dist: ptyprocess
